sqsfeedexport.py
scrapy_sqs_exporter-1.1.0.dist-info/METADATA
scrapy_sqs_exporter-1.1.0.dist-info/RECORD
scrapy_sqs_exporter-1.1.0.dist-info/WHEEL
scrapy_sqs_exporter-1.1.0.dist-info/top_level.txt
