Metadata-Version: 2.1
Name: scrapy-sqs-exporter
Version: 1.1.0
Summary: Scrapy extension for outputting scraped items to an Amazon SQS instance
Home-page: https://github.com/multiplechoice/scrapy-sqs-exporter
Author: aodj
Author-email: alexodonovanjones@gmail.com
License: MIT
Keywords: scrapy sqs
Platform: UNKNOWN
Requires-Dist: boto3
Requires-Dist: Scrapy
Requires-Dist: six
Requires-Dist: pytest
Requires-Dist: pytest-cov
Requires-Dist: moto
Requires-Dist: pytest-env
